<?xml version="1.0" encoding="utf-8" ?><dwsync><file name="admin.php" server="divinehealthdetox.com/www/" local="3493306682" remote="323953104381692864" Dst="-1" /><file name="denied.php" server="divinehealthdetox.com/www/" local="3493306682" remote="323953104381692864" Dst="-1" /><file name="emails-acct-update.php" server="divinehealthdetox.com/www/" local="3493306682" remote="323953104381692864" Dst="-1" /><file name="emails-activate.php" server="divinehealthdetox.com/www/" local="3493306682" remote="323953104381692864" Dst="-1" /><file name="emails-add-user.php" server="divinehealthdetox.com/www/" local="3493306682" remote="323953104381692864" Dst="-1" /><file name="emails-forgot.php" server="divinehealthdetox.com/www/" local="3493306682" remote="323953104381692864" Dst="-1" /><file name="emails-welcome.php" server="divinehealthdetox.com/www/" local="3493306682" remote="323953104381692864" Dst="-1" /><file name="header.php" server="divinehealthdetox.com/www/" local="3493306682" remote="323953104381692864" Dst="-1" /><file name="general-options.php" server="divinehealthdetox.com/www/" local="3493306682" remote="323953104381692864" Dst="-1" /><file name="index.php" server="divinehealthdetox.com/www/" local="3493306682" remote="323953104381692864" Dst="-1" /><file name="integration.php" server="divinehealthdetox.com/www/" local="3493306683" remote="323953104381692864" Dst="-1" /><file name="level-control.php" server="divinehealthdetox.com/www/" local="3493306683" remote="323953104381692864" Dst="-1" /><file name="level-create.php" server="divinehealthdetox.com/www/" local="3493306683" remote="323953104381692864" Dst="-1" /><file name="reports.php" server="divinehealthdetox.com/www/" local="3493306683" remote="323953104381692864" Dst="-1" /><file name="send-email.php" server="divinehealthdetox.com/www/" local="3493306683" remote="323953104381692864" Dst="-1" /><file name="settings.php" server="divinehealthdetox.com/www/" local="3493306683" remote="323953104381692864" Dst="-1" /><file name="update.php" server="divinehealthdetox.com/www/" local="3493306683" remote="323953104381692864" Dst="-1" /><file name="user-add.php" server="divinehealthdetox.com/www/" local="3493306683" remote="323953104381692864" Dst="-1" /><file name="user-control.php" server="divinehealthdetox.com/www/" local="3493306683" remote="323953104381692864" Dst="-1" /><file name="user-profiles.php" server="divinehealthdetox.com/www/" local="3493306683" remote="323953104381692864" Dst="-1" /></dwsync>